{
  "schema": "/objects/unstructured-quad-grid/1.0.1/unstructured-quad-grid.schema.json",
  "name": "Example Unstructured Quad Grid",
  "uuid": "00000000-0000-0000-0000-000000000000",
  "description": "This is example data to ensure the unstructured quadrilateral grid validates properly",
  "bounding_box": {
    "min_y": 5,
    "max_y": 10,
    "min_x": 0,
    "max_x": 10,
    "min_z": 5,
    "max_z": 10
  },
  "coordinate_reference_system": {
    "epsg_code": 1024
  },
  "quadrilaterals": {
    "vertices": {
      "width": 3,
      "data_type": "float64",
      "length": 4,
      "data": "abababababababababababababababababababababababababababababababab",
      "attributes": [
        {
          "name": "lithology",
          "attribute_type": "category",
          "nan_description": {
            "values": [
              -99
            ]
          },
          "attribute_description": {
            "discipline": "Geochemistry",
            "type": "Rock Type"
          },
          "values": {
            "data_type": "int32",
            "length": 4,
            "width": 1,
            "data": "abababababababababababababababababababababababababababababababab"
          },
          "table": {
            "keys_data_type": "int32",
            "values_data_type": "string",
            "length": 2,
            "data": "abababababababababababababababababababababababababababababababab"
          }
        }
      ]
    },
    "indices": {
      "width": 4,
      "data_type": "uint64",
      "length": 1,
      "data": "abababababababababababababababababababababababababababababababab",
      "attributes": [
        {
          "name": "chemicals",
          "attribute_type": "ensemble_category",
          "nan_description": {
            "values": [
              -99,
              -999
            ]
          },
          "attribute_description": {
            "discipline": "Geochemistry",
            "type": "Classification"
          },
          "values": {
            "data_type": "int32",
            "width": 5,
            "length": 1,
            "data": "abababababababababababababababababababababababababababababababab"
          },
          "table": {
            "keys_data_type": "int32",
            "values_data_type": "string",
            "length": 1,
            "data": "abababababababababababababababababababababababababababababababab"
          }
        }
      ]
    }
  },
  "tags": {},
  "extensions": {}
}
